copyingmock.py
copyingmock-0.2.dist-info/DESCRIPTION.rst
copyingmock-0.2.dist-info/METADATA
copyingmock-0.2.dist-info/RECORD
copyingmock-0.2.dist-info/WHEEL
copyingmock-0.2.dist-info/metadata.json
copyingmock-0.2.dist-info/top_level.txt
