Metadata-Version: 2.0
Name: copyingmock
Version: 0.2
Summary: A subclass of MagicMock that copies the arguments
Home-page: https://github.com/wimglenn/copyingmock
Author: Wim Glenn
Author-email: hey@wimglenn.com
License: MIT
Platform: UNKNOWN
Classifier: Programming Language :: Python :: 2
Classifier: Programming Language :: Python :: 3
Classifier: License :: OSI Approved :: MIT License
Classifier: Topic :: Software Development :: Libraries
Classifier: Intended Audience :: Developers
Requires-Dist: mock; python_version < "3.3"
